{"response": {"GeoObjectCollection": {"metaDataProperty": {"GeocoderResponseMetaData": {"request": "İsmet inönü mahallesi 1211/1 sokak no:19 kat:1 daire:4 (Altan Grup)", "results": "5", "found": "1"}}, "featureMember": [{"GeoObject": {"metaDataProperty": {"GeocoderMetaData": {"precision": "exact", "text": "İsmet İnönü Mah., 1211/1 Sok., No:19, Menemen, İzmir, Türkiye", "kind": "house", "Address": {"country_code": "TR", "formatted": "İsmet İnönü Mah., 1211/1 Sok., No:19, Menemen, İzmir, Türkiye", "Components": [{"kind": "country", "name": "Türkiye"}, {"kind": "province", "name": "İzmir"}, {"kind": "area", "name": "Menemen"}, {"kind": "district", "name": "İsmet İnönü Mah."}, {"kind": "street", "name": "1211/1 Sok."}, {"kind": "house", "name": "No:19"}]}, "AddressDetails": {"Country": {"AddressLine": "İsmet İnönü Mah., 1211/1 Sok., No:19, Menemen, İzmir, Türkiye", "CountryNameCode": "TR", "CountryName": "Türkiye", "AdministrativeArea": {"AdministrativeAreaName": "İzmir", "SubAdministrativeArea": {"SubAdministrativeAreaName": "Menemen", "Locality": {"DependentLocality": {"DependentLocalityName": "İsmet İnönü Mah.", "Thoroughfare": {"ThoroughfareName": "1211/1 Sok.", "Premise": {"PremiseNumber": "No:19"}}}}}}}}}}, "name": "1211/1 Sok., No:19", "description": "İsmet İnönü Mah., Menemen, İzmir, Türkiye", "boundedBy": {"Envelope": {"lowerCorner": "27.073022 38.590592", "upperCorner": "27.081232 38.597036"}}, "uri": "ymapsbm1://geo?data=CgoyMzk3NTQzOTQ3EkBUw7xya2l5ZSwgxLB6bWlyLCBNZW5lbWVuLCDEsHNtZXQgxLBuw7Zuw7wgTWFoLiwgMTIxMS8xIFNvay4sIDE5IgoN9J3YQRURYBpC", "Point": {"pos": "27.077127 38.593814"}}}]}}}