{"response": {"GeoObjectCollection": {"metaDataProperty": {"GeocoderResponseMetaData": {"request": "beşeylül mah. reddi ilhak cad. no:116 kat:2 kat:2 Alaşehir", "results": "5", "found": "1"}}, "featureMember": [{"GeoObject": {"metaDataProperty": {"GeocoderMetaData": {"precision": "exact", "text": "Reddi İlhak Cad., No:116, Alaşehir, Manisa, Türkiye", "kind": "house", "Address": {"country_code": "TR", "formatted": "Reddi İlhak Cad., No:116, Alaşehir, Manisa, Türkiye", "Components": [{"kind": "country", "name": "Türkiye"}, {"kind": "province", "name": "Manisa"}, {"kind": "area", "name": "Alaşehir"}, {"kind": "street", "name": "Reddi İlhak Cad."}, {"kind": "house", "name": "No:116"}]}, "AddressDetails": {"Country": {"AddressLine": "Reddi İlhak Cad., No:116, Alaşehir, Manisa, Türkiye", "CountryNameCode": "TR", "CountryName": "Türkiye", "AdministrativeArea": {"AdministrativeAreaName": "Manisa", "SubAdministrativeArea": {"SubAdministrativeAreaName": "Alaşehir", "Locality": {"Thoroughfare": {"ThoroughfareName": "Reddi İlhak Cad.", "Premise": {"PremiseNumber": "No:116"}}}}}}}}}, "name": "Reddi İlhak Cad., No:116", "description": "Alaşehir, Manisa, Türkiye", "boundedBy": {"Envelope": {"lowerCorner": "28.514216 38.347407", "upperCorner": "28.522427 38.353872"}}, "uri": "ymapsbm1://geo?data=CgoyNDA4NDYxNjU3EjNUw7xya2l5ZSwgTWFuaXNhLCBBbGHFn2VoaXIsIFJlZGRpIMSwbGhhayBDYWQuLCAxMTYiCg2FJeRBFQ5nGUI,", "Point": {"pos": "28.518321 38.350639"}}}]}}}