{"response": {"GeoObjectCollection": {"metaDataProperty": {"GeocoderResponseMetaData": {"request": "İzmir Urla Altıntaş mahallesi manolya sokak no 12 kat1 Daire 1 kat 1", "results": "5", "found": "1"}}, "featureMember": [{"GeoObject": {"metaDataProperty": {"GeocoderMetaData": {"precision": "exact", "text": "Manolya Sok., No:12, Urla, İzmir, Türkiye", "kind": "house", "Address": {"country_code": "TR", "formatted": "Manolya Sok., No:12, Urla, İzmir, Türkiye", "Components": [{"kind": "country", "name": "Türkiye"}, {"kind": "province", "name": "İzmir"}, {"kind": "area", "name": "Urla"}, {"kind": "street", "name": "Manolya Sok."}, {"kind": "house", "name": "No:12"}]}, "AddressDetails": {"Country": {"AddressLine": "Manolya Sok., No:12, Urla, İzmir, Türkiye", "CountryNameCode": "TR", "CountryName": "Türkiye", "AdministrativeArea": {"AdministrativeAreaName": "İzmir", "SubAdministrativeArea": {"SubAdministrativeAreaName": "Urla", "Locality": {"Thoroughfare": {"ThoroughfareName": "Manolya Sok.", "Premise": {"PremiseNumber": "No:12"}}}}}}}}}, "name": "Manolya Sok., No:12", "description": "Urla, İzmir, Türkiye", "boundedBy": {"Envelope": {"lowerCorner": "26.759034 38.313994", "upperCorner": "26.767244 38.320462"}}, "uri": "ymapsbm1://geo?data=CgoyMzk5NDg1NzQ4EihUw7xya2l5ZSwgxLB6bWlyLCBVcmxhLCBNYW5vbHlhIFNvay4sIDEyIgoN6RrWQRXYRBlC", "Point": {"pos": "26.763139 38.317228"}}}]}}}