{"response": {"GeoObjectCollection": {"metaDataProperty": {"GeocoderResponseMetaData": {"request": "Fatih mah Taksim caddesi no 23/2 kaire 1 Zemin kat izmir/tire FATİH TİRE İzmir", "results": "5", "found": "1"}}, "featureMember": [{"GeoObject": {"metaDataProperty": {"GeocoderMetaData": {"precision": "exact", "text": "Fatih Mah., Taksim Cad., No:23/2, Tire, İzmir, Türkiye", "kind": "house", "Address": {"country_code": "TR", "formatted": "Fatih Mah., Taksim Cad., No:23/2, Tire, İzmir, Türkiye", "Components": [{"kind": "country", "name": "Türkiye"}, {"kind": "province", "name": "İzmir"}, {"kind": "area", "name": "Tire"}, {"kind": "district", "name": "Fatih Mah."}, {"kind": "street", "name": "Taksim Cad."}, {"kind": "house", "name": "No:23/2"}]}, "AddressDetails": {"Country": {"AddressLine": "Fatih Mah., Taksim Cad., No:23/2, Tire, İzmir, Türkiye", "CountryNameCode": "TR", "CountryName": "Türkiye", "AdministrativeArea": {"AdministrativeAreaName": "İzmir", "SubAdministrativeArea": {"SubAdministrativeAreaName": "Tire", "Locality": {"DependentLocality": {"DependentLocalityName": "Fatih Mah.", "Thoroughfare": {"ThoroughfareName": "Taksim Cad.", "Premise": {"PremiseNumber": "No:23/2"}}}}}}}}}}, "name": "Taksim Cad., No:23/2", "description": "Fatih Mah., Tire, İzmir, Türkiye", "boundedBy": {"Envelope": {"lowerCorner": "27.71158 38.09668", "upperCorner": "27.719791 38.103168"}}, "uri": "ymapsbm1://geo?data=Cgo1NjMxOTgzMDY3EjVUw7xya2l5ZSwgxLB6bWlyLCBUaXJlLCBGYXRpaCBNYWguLCBUYWtzaW0gQ2FkLiwgMjMvMiIKDbm53UEVUmYYQg,,", "Point": {"pos": "27.715686 38.099924"}}}]}}}