{"response": {"GeoObjectCollection": {"metaDataProperty": {"GeocoderResponseMetaData": {"request": "Camikebir mahallesi izmir caddesi b blok no:36/A", "results": "5", "found": "2"}}, "featureMember": [{"GeoObject": {"metaDataProperty": {"GeocoderMetaData": {"precision": "exact", "text": "İzmir Cad., No:36A, Seferihisar, İzmir, Türkiye", "kind": "house", "Address": {"country_code": "TR", "formatted": "İzmir Cad., No:36A, Seferihisar, İzmir, Türkiye", "Components": [{"kind": "country", "name": "Türkiye"}, {"kind": "province", "name": "İzmir"}, {"kind": "area", "name": "Seferihisar"}, {"kind": "street", "name": "İzmir Cad."}, {"kind": "house", "name": "No:36A"}]}, "AddressDetails": {"Country": {"AddressLine": "İzmir Cad., No:36A, Seferihisar, İzmir, Türkiye", "CountryNameCode": "TR", "CountryName": "Türkiye", "AdministrativeArea": {"AdministrativeAreaName": "İzmir", "SubAdministrativeArea": {"SubAdministrativeAreaName": "Seferihisar", "Locality": {"Thoroughfare": {"ThoroughfareName": "İzmir Cad.", "Premise": {"PremiseNumber": "No:36A"}}}}}}}}}, "name": "İzmir Cad., No:36A", "description": "Seferihisar, İzmir, Türkiye", "boundedBy": {"Envelope": {"lowerCorner": "26.830468 38.18966", "upperCorner": "26.838678 38.196139"}}, "uri": "ymapsbm1://geo?data=CgoyMzk4MjM1MDcxEi9Uw7xya2l5ZSwgxLB6bWlyLCBTZWZlcmloaXNhciwgxLB6bWlyIENhZC4sIDM2QSIKDTSt1kEVh8UYQg,,", "Point": {"pos": "26.834573 38.1929"}}}, {"GeoObject": {"metaDataProperty": {"GeocoderMetaData": {"precision": "exact", "text": "Çitgöl Beldesi, Camii Kebir Mah., İzmir Cad., No:36A, Simav, Kütahya, Türkiye", "kind": "house", "Address": {"country_code": "TR", "formatted": "Çitgöl Beldesi, Camii Kebir Mah., İzmir Cad., No:36A, Simav, Kütahya, Türkiye", "Components": [{"kind": "country", "name": "Türkiye"}, {"kind": "province", "name": "Kütahya"}, {"kind": "area", "name": "Simav"}, {"kind": "district", "name": "Çitgöl Beldesi"}, {"kind": "district", "name": "Camii Kebir Mah."}, {"kind": "street", "name": "İzmir Cad."}, {"kind": "house", "name": "No:36A"}]}, "AddressDetails": {"Country": {"AddressLine": "Çitgöl Beldesi, Camii Kebir Mah., İzmir Cad., No:36A, Simav, Kütahya, Türkiye", "CountryNameCode": "TR", "CountryName": "Türkiye", "AdministrativeArea": {"AdministrativeAreaName": "Kütahya", "SubAdministrativeArea": {"SubAdministrativeAreaName": "Simav", "Locality": {"DependentLocality": {"DependentLocalityName": "Çitgöl Beldesi", "DependentLocality": {"DependentLocalityName": "Camii Kebir Mah.", "Thoroughfare": {"ThoroughfareName": "İzmir Cad.", "Premise": {"PremiseNumber": "No:36A"}}}}}}}}}}}, "name": "İzmir Cad., No:36A", "description": "Camii Kebir Mah., Çitgöl Beldesi, Simav, Kütahya, Türkiye", "boundedBy": {"Envelope": {"lowerCorner": "28.944096 39.11433", "upperCorner": "28.952306 39.120726"}}, "uri": "ymapsbm1://geo?data=Cgo2MjcxNTYzMTg2Ek9Uw7xya2l5ZSwgS8O8dGFoeWEsIFNpbWF2LCDDh2l0Z8O2bCBCZWxkZXNpLCBDYW1paSBLZWJpciBNYWguLCDEsHptaXIgQ2FkLiwgMzZBIgoN6pXnQRVZeBxC", "Point": {"pos": "28.948201 39.117528"}}}]}}}