{"response": {"GeoObjectCollection": {"metaDataProperty": {"GeocoderResponseMetaData": {"request": "DİCLE MAHALLESİ Dicle mahallesi 869 sokak no 24 daire 1 daire 6 buca izmir BUCA İZMIR Türkiye", "results": "5", "found": "1"}}, "featureMember": [{"GeoObject": {"metaDataProperty": {"GeocoderMetaData": {"precision": "exact", "text": "Ufuk Mah., 869 Sok., No:24, Buca, İzmir, Türkiye", "kind": "house", "Address": {"country_code": "TR", "formatted": "Ufuk Mah., 869 Sok., No:24, Buca, İzmir, Türkiye", "Components": [{"kind": "country", "name": "Türkiye"}, {"kind": "province", "name": "İzmir"}, {"kind": "area", "name": "Buca"}, {"kind": "district", "name": "Ufuk Mah."}, {"kind": "street", "name": "869 Sok."}, {"kind": "house", "name": "No:24"}]}, "AddressDetails": {"Country": {"AddressLine": "Ufuk Mah., 869 Sok., No:24, Buca, İzmir, Türkiye", "CountryNameCode": "TR", "CountryName": "Türkiye", "AdministrativeArea": {"AdministrativeAreaName": "İzmir", "SubAdministrativeArea": {"SubAdministrativeAreaName": "Buca", "Locality": {"DependentLocality": {"DependentLocalityName": "Ufuk Mah.", "Thoroughfare": {"ThoroughfareName": "869 Sok.", "Premise": {"PremiseNumber": "No:24"}}}}}}}}}}, "name": "869 Sok., No:24", "description": "Ufuk Mah., Buca, İzmir, Türkiye", "boundedBy": {"Envelope": {"lowerCorner": "27.159009 38.397235", "upperCorner": "27.167219 38.403696"}}, "uri": "ymapsbm1://geo?data=CgoyMzk4MjMxOTc5Ei9Uw7xya2l5ZSwgxLB6bWlyLCBCdWNhLCBVZnVrIE1haC4sIDg2OSBTb2suLCAyNCIKDRBO2UEVFJoZQg,,", "Point": {"pos": "27.163114 38.400466"}}}]}}}