{"response": {"GeoObjectCollection": {"metaDataProperty": {"GeocoderResponseMetaData": {"request": "320. Sk. No:6 -1 CUMHURİYET DİKİLİ İzmir", "results": "5", "found": "2"}}, "featureMember": [{"GeoObject": {"metaDataProperty": {"GeocoderMetaData": {"precision": "number", "text": "Cumhuriyet Mah., 320 Sok., No:6/1, Dikili, İzmir, Türkiye", "kind": "house", "Address": {"country_code": "TR", "formatted": "Cumhuriyet Mah., 320 Sok., No:6/1, Dikili, İzmir, Türkiye", "Components": [{"kind": "country", "name": "Türkiye"}, {"kind": "province", "name": "İzmir"}, {"kind": "area", "name": "Dikili"}, {"kind": "district", "name": "Cumhuriyet Mah."}, {"kind": "street", "name": "320 Sok."}, {"kind": "house", "name": "No:6/1"}]}, "AddressDetails": {"Country": {"AddressLine": "Cumhuriyet Mah., 320 Sok., No:6/1, Dikili, İzmir, Türkiye", "CountryNameCode": "TR", "CountryName": "Türkiye", "AdministrativeArea": {"AdministrativeAreaName": "İzmir", "SubAdministrativeArea": {"SubAdministrativeAreaName": "Dikili", "Locality": {"DependentLocality": {"DependentLocalityName": "Cumhuriyet Mah.", "Thoroughfare": {"ThoroughfareName": "320 Sok.", "Premise": {"PremiseNumber": "No:6/1"}}}}}}}}}}, "name": "320 Sok., No:6/1", "description": "Cumhuriyet Mah., Dikili, İzmir, Türkiye", "boundedBy": {"Envelope": {"lowerCorner": "26.887331 39.077573", "upperCorner": "26.895542 39.083972"}}, "uri": "ymapsbm1://geo?data=CgoyMzk3NDUzNTA3EjhUw7xya2l5ZSwgxLB6bWlyLCBEaWtpbGksIEN1bWh1cml5ZXQgTWFoLiwgMzIwIFNvay4sIDYvMSIKDagh10EVtlIcQg,,", "Point": {"pos": "26.891436 39.080773"}}}, {"GeoObject": {"metaDataProperty": {"GeocoderMetaData": {"precision": "exact", "text": "Cumhuriyet Mah., 320 Sok., No:6, Dikili, İzmir, Türkiye", "kind": "house", "Address": {"country_code": "TR", "formatted": "Cumhuriyet Mah., 320 Sok., No:6, Dikili, İzmir, Türkiye", "Components": [{"kind": "country", "name": "Türkiye"}, {"kind": "province", "name": "İzmir"}, {"kind": "area", "name": "Dikili"}, {"kind": "district", "name": "Cumhuriyet Mah."}, {"kind": "street", "name": "320 Sok."}, {"kind": "house", "name": "No:6"}]}, "AddressDetails": {"Country": {"AddressLine": "Cumhuriyet Mah., 320 Sok., No:6, Dikili, İzmir, Türkiye", "CountryNameCode": "TR", "CountryName": "Türkiye", "AdministrativeArea": {"AdministrativeAreaName": "İzmir", "SubAdministrativeArea": {"SubAdministrativeAreaName": "Dikili", "Locality": {"DependentLocality": {"DependentLocalityName": "Cumhuriyet Mah.", "Thoroughfare": {"ThoroughfareName": "320 Sok.", "Premise": {"PremiseNumber": "No:6"}}}}}}}}}}, "name": "320 Sok., No:6", "description": "Cumhuriyet Mah., Dikili, İzmir, Türkiye", "boundedBy": {"Envelope": {"lowerCorner": "26.887349 39.077503", "upperCorner": "26.89556 39.083902"}}, "uri": "ymapsbm1://geo?data=CgoyMzk3NDUzNTA1EjZUw7xya2l5ZSwgxLB6bWlyLCBEaWtpbGksIEN1bWh1cml5ZXQgTWFoLiwgMzIwIFNvay4sIDYiCg2xIddBFaRSHEI,", "Point": {"pos": "26.891454 39.080703"}}}]}}}