{"response": {"GeoObjectCollection": {"metaDataProperty": {"GeocoderResponseMetaData": {"request": "mansuroğlu mah. 288 sokak no 6 kat 3 daire 412", "results": "5", "found": "1"}}, "featureMember": [{"GeoObject": {"metaDataProperty": {"GeocoderMetaData": {"precision": "exact", "text": "Mansuroğlu Mah., 288 Sok., No:6, Bayraklı, İzmir, Türkiye", "kind": "house", "Address": {"country_code": "TR", "formatted": "Mansuroğlu Mah., 288 Sok., No:6, Bayraklı, İzmir, Türkiye", "Components": [{"kind": "country", "name": "Türkiye"}, {"kind": "province", "name": "İzmir"}, {"kind": "area", "name": "Bayraklı"}, {"kind": "district", "name": "Mansuroğlu Mah."}, {"kind": "street", "name": "288 Sok."}, {"kind": "house", "name": "No:6"}]}, "AddressDetails": {"Country": {"AddressLine": "Mansuroğlu Mah., 288 Sok., No:6, Bayraklı, İzmir, Türkiye", "CountryNameCode": "TR", "CountryName": "Türkiye", "AdministrativeArea": {"AdministrativeAreaName": "İzmir", "SubAdministrativeArea": {"SubAdministrativeAreaName": "Bayraklı", "Locality": {"DependentLocality": {"DependentLocalityName": "Mansuroğlu Mah.", "Thoroughfare": {"ThoroughfareName": "288 Sok.", "Premise": {"PremiseNumber": "No:6"}}}}}}}}}}, "name": "288 Sok., No:6", "description": "Mansuroğlu Mah., Bayraklı, İzmir, Türkiye", "boundedBy": {"Envelope": {"lowerCorner": "27.179526 38.447114", "upperCorner": "27.187737 38.453571"}}, "uri": "ymapsbm1://geo?data=CgoyMzk2Mzk5MjY4EjpUw7xya2l5ZSwgxLB6bWlyLCBCYXlyYWtsxLEsIE1hbnN1cm_En2x1IE1haC4sIDI4OCBTb2suLCA2IgoNFnjZQRUnzRlC", "Point": {"pos": "27.183631 38.450342"}}}]}}}