{"response": {"GeoObjectCollection": {"metaDataProperty": {"GeocoderResponseMetaData": {"request": "MAVİŞEHİR Mah. 2040/5. Sk. Bina No : 6 Daire No : 22 Kat : 10 KARŞIYAKA / İzmir", "results": "5", "found": "1"}}, "featureMember": [{"GeoObject": {"metaDataProperty": {"GeocoderMetaData": {"precision": "exact", "text": "Mavişehir Mah., 2040/5 Sok., No:6, Karşıyaka, İzmir, Türkiye", "kind": "house", "Address": {"country_code": "TR", "formatted": "Mavişehir Mah., 2040/5 Sok., No:6, Karşıyaka, İzmir, Türkiye", "Components": [{"kind": "country", "name": "Türkiye"}, {"kind": "province", "name": "İzmir"}, {"kind": "area", "name": "Karşıyaka"}, {"kind": "district", "name": "Mavişehir Mah."}, {"kind": "street", "name": "2040/5 Sok."}, {"kind": "house", "name": "No:6"}]}, "AddressDetails": {"Country": {"AddressLine": "Mavişehir Mah., 2040/5 Sok., No:6, Karşıyaka, İzmir, Türkiye", "CountryNameCode": "TR", "CountryName": "Türkiye", "AdministrativeArea": {"AdministrativeAreaName": "İzmir", "SubAdministrativeArea": {"SubAdministrativeAreaName": "Karşıyaka", "Locality": {"DependentLocality": {"DependentLocalityName": "Mavişehir Mah.", "Thoroughfare": {"ThoroughfareName": "2040/5 Sok.", "Premise": {"PremiseNumber": "No:6"}}}}}}}}}}, "name": "2040/5 Sok., No:6", "description": "Mavişehir Mah., Karşıyaka, İzmir, Türkiye", "boundedBy": {"Envelope": {"lowerCorner": "27.066114 38.467337", "upperCorner": "27.074324 38.473792"}}, "uri": "ymapsbm1://geo?data=CgoyMzk2Mjg2NTYwEj5Uw7xya2l5ZSwgxLB6bWlyLCBLYXLFn8SxeWFrYSwgTWF2acWfZWhpciBNYWguLCAyMDQwLzUgU29rLiwgNiIKDdCP2EEV3OEZQg,,", "Point": {"pos": "27.070219 38.470564"}}}]}}}