{"response": {"GeoObjectCollection": {"metaDataProperty": {"GeocoderResponseMetaData": {"request": "2432/1 SOKAK NO:33", "results": "5", "found": "1"}}, "featureMember": [{"GeoObject": {"metaDataProperty": {"GeocoderMetaData": {"precision": "exact", "text": "Karşıyaka Mah., 2432/1. Sok., No:33, Pamukkale, Denizli, Türkiye", "kind": "house", "Address": {"country_code": "TR", "formatted": "Karşıyaka Mah., 2432/1. Sok., No:33, Pamukkale, Denizli, Türkiye", "Components": [{"kind": "country", "name": "Türkiye"}, {"kind": "province", "name": "Denizli"}, {"kind": "area", "name": "Pamukkale"}, {"kind": "district", "name": "Karşıyaka Mah."}, {"kind": "street", "name": "2432/1. Sok."}, {"kind": "house", "name": "No:33"}]}, "AddressDetails": {"Country": {"AddressLine": "Karşıyaka Mah., 2432/1. Sok., No:33, Pamukkale, Denizli, Türkiye", "CountryNameCode": "TR", "CountryName": "Türkiye", "AdministrativeArea": {"AdministrativeAreaName": "Denizli", "SubAdministrativeArea": {"SubAdministrativeAreaName": "Pamukkale", "Locality": {"DependentLocality": {"DependentLocalityName": "Karşıyaka Mah.", "Thoroughfare": {"ThoroughfareName": "2432/1. Sok.", "Premise": {"PremiseNumber": "No:33"}}}}}}}}}}, "name": "2432/1. Sok., No:33", "description": "Karşıyaka Mah., Pamukkale, Denizli, Türkiye", "boundedBy": {"Envelope": {"lowerCorner": "29.111721 37.801552", "upperCorner": "29.119932 37.808067"}}, "uri": "ymapsbm1://geo?data=CgozMTA2MDA3Nzc5EkBUw7xya2l5ZSwgRGVuaXpsaSwgUGFtdWtrYWxlLCBLYXLFn8SxeWFrYSBNYWguLCAyNDMyLzEuIFNvay4sIDMzIgoNN-3oQRUhOBdC", "Point": {"pos": "29.115827 37.804809"}}}]}}}