{"response": {"GeoObjectCollection": {"metaDataProperty": {"GeocoderResponseMetaData": {"request": "Dilek sitesi Levent sokak no 1-18 Urla İzmir", "results": "5", "found": "1"}}, "featureMember": [{"GeoObject": {"metaDataProperty": {"GeocoderMetaData": {"precision": "exact", "text": "Yenikent Mah., Levent Sok., No:1/18, Urla, İzmir, Türkiye", "kind": "house", "Address": {"country_code": "TR", "formatted": "Yenikent Mah., Levent Sok., No:1/18, Urla, İzmir, Türkiye", "Components": [{"kind": "country", "name": "Türkiye"}, {"kind": "province", "name": "İzmir"}, {"kind": "area", "name": "Urla"}, {"kind": "district", "name": "Yenikent Mah."}, {"kind": "street", "name": "Levent Sok."}, {"kind": "house", "name": "No:1/18"}]}, "AddressDetails": {"Country": {"AddressLine": "Yenikent Mah., Levent Sok., No:1/18, Urla, İzmir, Türkiye", "CountryNameCode": "TR", "CountryName": "Türkiye", "AdministrativeArea": {"AdministrativeAreaName": "İzmir", "SubAdministrativeArea": {"SubAdministrativeAreaName": "Urla", "Locality": {"DependentLocality": {"DependentLocalityName": "Yenikent Mah.", "Thoroughfare": {"ThoroughfareName": "Levent Sok.", "Premise": {"PremiseNumber": "No:1/18"}}}}}}}}}}, "name": "Levent Sok., No:1/18", "description": "Yenikent Mah., Urla, İzmir, Türkiye", "boundedBy": {"Envelope": {"lowerCorner": "26.765178 38.327412", "upperCorner": "26.773389 38.333879"}}, "uri": "ymapsbm1://geo?data=CgoyMzk4NjI2NjEzEjhUw7xya2l5ZSwgxLB6bWlyLCBVcmxhLCBZZW5pa2VudCBNYWguLCBMZXZlbnQgU29rLiwgMS8xOCIKDXwn1kEVlVIZQg,,", "Point": {"pos": "26.769283 38.330645"}}}]}}}