{"response": {"GeoObjectCollection": {"metaDataProperty": {"GeocoderResponseMetaData": {"request": "Mustafa kemal mahallesi 2. Çam Sokak no 15 daire 1", "results": "5", "found": "1"}}, "featureMember": [{"GeoObject": {"metaDataProperty": {"GeocoderMetaData": {"precision": "exact", "text": "Mustafa Kemal Mah., 2. Çam Sok., No:15, Turgutlu, Manisa, Türkiye", "kind": "house", "Address": {"country_code": "TR", "formatted": "Mustafa Kemal Mah., 2. Çam Sok., No:15, Turgutlu, Manisa, Türkiye", "Components": [{"kind": "country", "name": "Türkiye"}, {"kind": "province", "name": "Manisa"}, {"kind": "area", "name": "Turgutlu"}, {"kind": "district", "name": "Mustafa Kemal Mah."}, {"kind": "street", "name": "2. Çam Sok."}, {"kind": "house", "name": "No:15"}]}, "AddressDetails": {"Country": {"AddressLine": "Mustafa Kemal Mah., 2. Çam Sok., No:15, Turgutlu, Manisa, Türkiye", "CountryNameCode": "TR", "CountryName": "Türkiye", "AdministrativeArea": {"AdministrativeAreaName": "Manisa", "SubAdministrativeArea": {"SubAdministrativeAreaName": "Turgutlu", "Locality": {"DependentLocality": {"DependentLocalityName": "Mustafa Kemal Mah.", "Thoroughfare": {"ThoroughfareName": "2. Çam Sok.", "Premise": {"PremiseNumber": "No:15"}}}}}}}}}}, "name": "2. Çam Sok., No:15", "description": "Mustafa Kemal Mah., Turgutlu, Manisa, Türkiye", "boundedBy": {"Envelope": {"lowerCorner": "27.696444 38.50298", "upperCorner": "27.704654 38.509431"}}, "uri": "ymapsbm1://geo?data=CgoyNDA4MzYyODg3EkBUw7xya2l5ZSwgTWFuaXNhLCBUdXJndXRsdSwgTXVzdGFmYSBLZW1hbCBNYWguLCAyLiDDh2FtIFNvay4sIDE1IgoNuprdQRVcBhpC", "Point": {"pos": "27.700549 38.506206"}}}]}}}