{"response": {"GeoObjectCollection": {"metaDataProperty": {"GeocoderResponseMetaData": {"request": "Dedebaşı Mah.ordu bulvarı no112 DEDEBAŞI KARŞIYAKA İzmir", "results": "5", "found": "1"}}, "featureMember": [{"GeoObject": {"metaDataProperty": {"GeocoderMetaData": {"precision": "exact", "text": "Ordu Blv., No:112, Karşıyaka, İzmir, Türkiye", "kind": "house", "Address": {"country_code": "TR", "formatted": "Ordu Blv., No:112, Karşıyaka, İzmir, Türkiye", "Components": [{"kind": "country", "name": "Türkiye"}, {"kind": "province", "name": "İzmir"}, {"kind": "area", "name": "Karşıyaka"}, {"kind": "street", "name": "Ordu Blv."}, {"kind": "house", "name": "No:112"}]}, "AddressDetails": {"Country": {"AddressLine": "Ordu Blv., No:112, Karşıyaka, İzmir, Türkiye", "CountryNameCode": "TR", "CountryName": "Türkiye", "AdministrativeArea": {"AdministrativeAreaName": "İzmir", "SubAdministrativeArea": {"SubAdministrativeAreaName": "Karşıyaka", "Locality": {"Thoroughfare": {"ThoroughfareName": "Ordu Blv.", "Premise": {"PremiseNumber": "No:112"}}}}}}}}}, "name": "Ordu Blv., No:112", "description": "Karşıyaka, İzmir, Türkiye", "boundedBy": {"Envelope": {"lowerCorner": "27.101148 38.466306", "upperCorner": "27.109359 38.472761"}}, "uri": "ymapsbm1://geo?data=CgoyMzk4MDgzMzQwEi1Uw7xya2l5ZSwgxLB6bWlyLCBLYXLFn8SxeWFrYSwgT3JkdSBCbHYuLCAxMTIiCg2N19hBFc7gGUI,", "Point": {"pos": "27.105253 38.469533"}}}]}}}