{"response": {"GeoObjectCollection": {"metaDataProperty": {"GeocoderResponseMetaData": {"request": "8211/11 sk. no:11 d:5 çağlayan apt. B blok Çiğli İzmir", "results": "5", "found": "1"}}, "featureMember": [{"GeoObject": {"metaDataProperty": {"GeocoderMetaData": {"precision": "exact", "text": "Ataşehir Mah., 8211/11. Sok., No:11, Çiğli, İzmir, Türkiye", "kind": "house", "Address": {"country_code": "TR", "formatted": "Ataşehir Mah., 8211/11. Sok., No:11, Çiğli, İzmir, Türkiye", "Components": [{"kind": "country", "name": "Türkiye"}, {"kind": "province", "name": "İzmir"}, {"kind": "area", "name": "Çiğli"}, {"kind": "district", "name": "Ataşehir Mah."}, {"kind": "street", "name": "8211/11. Sok."}, {"kind": "house", "name": "No:11"}]}, "AddressDetails": {"Country": {"AddressLine": "Ataşehir Mah., 8211/11. Sok., No:11, Çiğli, İzmir, Türkiye", "CountryNameCode": "TR", "CountryName": "Türkiye", "AdministrativeArea": {"AdministrativeAreaName": "İzmir", "SubAdministrativeArea": {"SubAdministrativeAreaName": "Çiğli", "Locality": {"DependentLocality": {"DependentLocalityName": "Ataşehir Mah.", "Thoroughfare": {"ThoroughfareName": "8211/11. Sok.", "Premise": {"PremiseNumber": "No:11"}}}}}}}}}}, "name": "8211/11. Sok., No:11", "description": "Ataşehir Mah., Çiğli, İzmir, Türkiye", "boundedBy": {"Envelope": {"lowerCorner": "27.05404 38.483275", "upperCorner": "27.062251 38.489729"}}, "uri": "ymapsbm1://geo?data=CgoyMzk4Njc0MzUxEjxUw7xya2l5ZSwgxLB6bWlyLCDDh2nEn2xpLCBBdGHFn2VoaXIgTWFoLiwgODIxMS8xMS4gU29rLiwgMTEiCg0Ud9hBFS3yGUI,", "Point": {"pos": "27.058146 38.486502"}}}]}}}