{"response": {"GeoObjectCollection": {"metaDataProperty": {"GeocoderResponseMetaData": {"request": "Yedi Eylül Mh. Kervan You Caddesi No.125 Kat.2 TURGUTLU MANİSA", "results": "5", "found": "2"}}, "featureMember": [{"GeoObject": {"metaDataProperty": {"GeocoderMetaData": {"precision": "number", "text": "Kervan Yolu, No:125, Turgutlu, Manisa, Türkiye", "kind": "house", "Address": {"country_code": "TR", "formatted": "Kervan Yolu, No:125, Turgutlu, Manisa, Türkiye", "Components": [{"kind": "country", "name": "Türkiye"}, {"kind": "province", "name": "Manisa"}, {"kind": "area", "name": "Turgutlu"}, {"kind": "street", "name": "Kervan Yolu"}, {"kind": "house", "name": "No:125"}]}, "AddressDetails": {"Country": {"AddressLine": "Kervan Yolu, No:125, Turgutlu, Manisa, Türkiye", "CountryNameCode": "TR", "CountryName": "Türkiye", "AdministrativeArea": {"AdministrativeAreaName": "Manisa", "SubAdministrativeArea": {"SubAdministrativeAreaName": "Turgutlu", "Locality": {"Thoroughfare": {"ThoroughfareName": "Kervan Yolu", "Premise": {"PremiseNumber": "No:125"}}}}}}}}}, "name": "Kervan Yolu, No:125", "description": "Turgutlu, Manisa, Türkiye", "boundedBy": {"Envelope": {"lowerCorner": "27.697701 38.501046", "upperCorner": "27.705912 38.507497"}}, "uri": "ymapsbm1://geo?data=CgoyNTMyNjI0Mzc2EixUw7xya2l5ZSwgTWFuaXNhLCBUdXJndXRsdSwgS2VydmFuIFlvbHUsIDEyNSIKDUud3UEVYQQaQg,,", "Point": {"pos": "27.701807 38.504272"}}}, {"GeoObject": {"metaDataProperty": {"GeocoderMetaData": {"precision": "exact", "text": "Yedi Eylül Yolu Cad., No:125, Turgutlu, Manisa, Türkiye", "kind": "house", "Address": {"country_code": "TR", "formatted": "Yedi Eylül Yolu Cad., No:125, Turgutlu, Manisa, Türkiye", "Components": [{"kind": "country", "name": "Türkiye"}, {"kind": "province", "name": "Manisa"}, {"kind": "area", "name": "Turgutlu"}, {"kind": "street", "name": "Yedi Eylül Yolu Cad."}, {"kind": "house", "name": "No:125"}]}, "AddressDetails": {"Country": {"AddressLine": "Yedi Eylül Yolu Cad., No:125, Turgutlu, Manisa, Türkiye", "CountryNameCode": "TR", "CountryName": "Türkiye", "AdministrativeArea": {"AdministrativeAreaName": "Manisa", "SubAdministrativeArea": {"SubAdministrativeAreaName": "Turgutlu", "Locality": {"Thoroughfare": {"ThoroughfareName": "Yedi Eylül Yolu Cad.", "Premise": {"PremiseNumber": "No:125"}}}}}}}}}, "name": "Yedi Eylül Yolu Cad., No:125", "description": "Turgutlu, Manisa, Türkiye", "boundedBy": {"Envelope": {"lowerCorner": "27.712802 38.492249", "upperCorner": "27.721013 38.498702"}}, "uri": "ymapsbm1://geo?data=CgoyNDEzMjM3MTc4EjZUw7xya2l5ZSwgTWFuaXNhLCBUdXJndXRsdSwgWWVkaSBFeWzDvGwgWW9sdSBDYWQuLCAxMjUiCg08vN1BFV37GUI,", "Point": {"pos": "27.716907 38.495476"}}}]}}}