{"response": {"GeoObjectCollection": {"metaDataProperty": {"GeocoderResponseMetaData": {"request": "ORTA Mah. Orta mahalle İncealiler sokak No:8 kat:3 Tavas/Denizli", "results": "5", "found": "1"}}, "featureMember": [{"GeoObject": {"metaDataProperty": {"GeocoderMetaData": {"precision": "exact", "text": "Orta Mah., İnce Aliler Sok., No:8, Tavas, Denizli, Türkiye", "kind": "house", "Address": {"country_code": "TR", "formatted": "Orta Mah., İnce Aliler Sok., No:8, Tavas, Denizli, Türkiye", "Components": [{"kind": "country", "name": "Türkiye"}, {"kind": "province", "name": "Denizli"}, {"kind": "area", "name": "Tavas"}, {"kind": "district", "name": "Orta Mah."}, {"kind": "street", "name": "İnce Aliler Sok."}, {"kind": "house", "name": "No:8"}]}, "AddressDetails": {"Country": {"AddressLine": "Orta Mah., İnce Aliler Sok., No:8, Tavas, Denizli, Türkiye", "CountryNameCode": "TR", "CountryName": "Türkiye", "AdministrativeArea": {"AdministrativeAreaName": "Denizli", "SubAdministrativeArea": {"SubAdministrativeAreaName": "Tavas", "Locality": {"DependentLocality": {"DependentLocalityName": "Orta Mah.", "Thoroughfare": {"ThoroughfareName": "İnce Aliler Sok.", "Premise": {"PremiseNumber": "No:8"}}}}}}}}}}, "name": "İnce Aliler Sok., No:8", "description": "Orta Mah., Tavas, Denizli, Türkiye", "boundedBy": {"Envelope": {"lowerCorner": "29.065386 37.569976", "upperCorner": "29.073597 37.576511"}}, "uri": "ymapsbm1://geo?data=CgoyNDAzMzA1NzU3EjlUw7xya2l5ZSwgRGVuaXpsaSwgVGF2YXMsIE9ydGEgTWFoLiwgxLBuY2UgQWxpbGVyIFNvay4sIDgiCg1RjuhBFf9KFkI,", "Point": {"pos": "29.069492 37.573244"}}}]}}}