{"response": {"GeoObjectCollection": {"metaDataProperty": {"GeocoderResponseMetaData": {"request": "Atatürk mahallesi 579. sokak no7 İzmir Güzelbahçe ATATÜRK GÜZELBAHÇE İzmir", "results": "5", "found": "1"}}, "featureMember": [{"GeoObject": {"metaDataProperty": {"GeocoderMetaData": {"precision": "exact", "text": "Atatürk Mah., 579 Sok., No:7, Güzelbahçe, İzmir, Türkiye", "kind": "house", "Address": {"country_code": "TR", "formatted": "Atatürk Mah., 579 Sok., No:7, Güzelbahçe, İzmir, Türkiye", "Components": [{"kind": "country", "name": "Türkiye"}, {"kind": "province", "name": "İzmir"}, {"kind": "area", "name": "Güzelbahçe"}, {"kind": "district", "name": "Atatürk Mah."}, {"kind": "street", "name": "579 Sok."}, {"kind": "house", "name": "No:7"}]}, "AddressDetails": {"Country": {"AddressLine": "Atatürk Mah., 579 Sok., No:7, Güzelbahçe, İzmir, Türkiye", "CountryNameCode": "TR", "CountryName": "Türkiye", "AdministrativeArea": {"AdministrativeAreaName": "İzmir", "SubAdministrativeArea": {"SubAdministrativeAreaName": "Güzelbahçe", "Locality": {"DependentLocality": {"DependentLocalityName": "Atatürk Mah.", "Thoroughfare": {"ThoroughfareName": "579 Sok.", "Premise": {"PremiseNumber": "No:7"}}}}}}}}}}, "name": "579 Sok., No:7", "description": "Atatürk Mah., Güzelbahçe, İzmir, Türkiye", "boundedBy": {"Envelope": {"lowerCorner": "26.885193 38.351474", "upperCorner": "26.893404 38.35794"}}, "uri": "ymapsbm1://geo?data=CgoyMzk4NTcxNTU5EjpUw7xya2l5ZSwgxLB6bWlyLCBHw7x6ZWxiYWjDp2UsIEF0YXTDvHJrIE1haC4sIDU3OSBTb2suLCA3IgoNSB3XQRU4axlC", "Point": {"pos": "26.889298 38.354707"}}}]}}}