{"response": {"GeoObjectCollection": {"metaDataProperty": {"GeocoderResponseMetaData": {"request": "3011. Sk. No :74/a SAKARYA MAH", "results": "5", "found": "1"}}, "featureMember": [{"GeoObject": {"metaDataProperty": {"GeocoderMetaData": {"precision": "exact", "text": "3011. Sok., No:74A, Çeşme, İzmir, Türkiye", "kind": "house", "Address": {"country_code": "TR", "formatted": "3011. Sok., No:74A, Çeşme, İzmir, Türkiye", "Components": [{"kind": "country", "name": "Türkiye"}, {"kind": "province", "name": "İzmir"}, {"kind": "area", "name": "Çeşme"}, {"kind": "street", "name": "3011. Sok."}, {"kind": "house", "name": "No:74A"}]}, "AddressDetails": {"Country": {"AddressLine": "3011. Sok., No:74A, Çeşme, İzmir, Türkiye", "CountryNameCode": "TR", "CountryName": "Türkiye", "AdministrativeArea": {"AdministrativeAreaName": "İzmir", "SubAdministrativeArea": {"SubAdministrativeAreaName": "Çeşme", "Locality": {"Thoroughfare": {"ThoroughfareName": "3011. Sok.", "Premise": {"PremiseNumber": "No:74A"}}}}}}}}}, "name": "3011. Sok., No:74A", "description": "Çeşme, İzmir, Türkiye", "boundedBy": {"Envelope": {"lowerCorner": "26.299366 38.334367", "upperCorner": "26.307576 38.340834"}}, "uri": "ymapsbm1://geo?data=CgoyMzk3NTAwOTQ5EipUw7xya2l5ZSwgxLB6bWlyLCDDh2XFn21lLCAzMDExLiBTb2suLCA3NEEiCg2DbdJBFbVZGUI,", "Point": {"pos": "26.303471 38.337601"}}}]}}}