{"response": {"GeoObjectCollection": {"metaDataProperty": {"GeocoderResponseMetaData": {"request": "İsmetpasa mah. 52 sk no48 kat3. Daire 21", "results": "5", "found": "2"}}, "featureMember": [{"GeoObject": {"metaDataProperty": {"GeocoderMetaData": {"precision": "exact", "text": "İsmetpaşa Mah., 52 Sok., No:48, Dikili, İzmir, Türkiye", "kind": "house", "Address": {"country_code": "TR", "formatted": "İsmetpaşa Mah., 52 Sok., No:48, Dikili, İzmir, Türkiye", "Components": [{"kind": "country", "name": "Türkiye"}, {"kind": "province", "name": "İzmir"}, {"kind": "area", "name": "Dikili"}, {"kind": "district", "name": "İsmetpaşa Mah."}, {"kind": "street", "name": "52 Sok."}, {"kind": "house", "name": "No:48"}]}, "AddressDetails": {"Country": {"AddressLine": "İsmetpaşa Mah., 52 Sok., No:48, Dikili, İzmir, Türkiye", "CountryNameCode": "TR", "CountryName": "Türkiye", "AdministrativeArea": {"AdministrativeAreaName": "İzmir", "SubAdministrativeArea": {"SubAdministrativeAreaName": "Dikili", "Locality": {"DependentLocality": {"DependentLocalityName": "İsmetpaşa Mah.", "Thoroughfare": {"ThoroughfareName": "52 Sok.", "Premise": {"PremiseNumber": "No:48"}}}}}}}}}}, "name": "52 Sok., No:48", "description": "İsmetpaşa Mah., Dikili, İzmir, Türkiye", "boundedBy": {"Envelope": {"lowerCorner": "26.889819 39.068281", "upperCorner": "26.89803 39.074681"}}, "uri": "ymapsbm1://geo?data=CgoyMzk3MzY0OTg1EjdUw7xya2l5ZSwgxLB6bWlyLCBEaWtpbGksIMSwc21ldHBhxZ9hIE1haC4sIDUyIFNvay4sIDQ4IgoNwCbXQRUzSRxC", "Point": {"pos": "26.893925 39.071481"}}}, {"GeoObject": {"metaDataProperty": {"GeocoderMetaData": {"precision": "exact", "text": "Davutpaşa Mah., 52. Sok., No:48, Esenler, İstanbul, Türkiye", "kind": "house", "Address": {"country_code": "TR", "formatted": "Davutpaşa Mah., 52. Sok., No:48, Esenler, İstanbul, Türkiye", "Components": [{"kind": "country", "name": "Türkiye"}, {"kind": "province", "name": "İstanbul"}, {"kind": "area", "name": "Esenler"}, {"kind": "district", "name": "Davutpaşa Mah."}, {"kind": "street", "name": "52. Sok."}, {"kind": "house", "name": "No:48"}]}, "AddressDetails": {"Country": {"AddressLine": "Davutpaşa Mah., 52. Sok., No:48, Esenler, İstanbul, Türkiye", "CountryNameCode": "TR", "CountryName": "Türkiye", "AdministrativeArea": {"AdministrativeAreaName": "İstanbul", "SubAdministrativeArea": {"SubAdministrativeAreaName": "Esenler", "Locality": {"DependentLocality": {"DependentLocalityName": "Davutpaşa Mah.", "Thoroughfare": {"ThoroughfareName": "52. Sok.", "Premise": {"PremiseNumber": "No:48"}}}}}}}}}}, "name": "52. Sok., No:48", "description": "Davutpaşa Mah., Esenler, İstanbul, Türkiye", "boundedBy": {"Envelope": {"lowerCorner": "28.888607 41.029098", "upperCorner": "28.896817 41.035315"}}, "uri": "ymapsbm1://geo?data=CgoyNDAyMDY4NTkzEjtUw7xya2l5ZSwgxLBzdGFuYnVsLCBFc2VubGVyLCBEYXZ1dHBhxZ9hIE1haC4sIDUyLiBTb2suLCA0OCIKDUgk50EV-iAkQg,,", "Point": {"pos": "28.892712 41.032207"}}}]}}}