{"response": {"GeoObjectCollection": {"metaDataProperty": {"GeocoderResponseMetaData": {"request": "1620/81. Sk. No:5 Kat:1 Daire:2 İzmir / bayraklı CENGİZHAN BAYRAKLI İzmir", "results": "5", "found": "1"}}, "featureMember": [{"GeoObject": {"metaDataProperty": {"GeocoderMetaData": {"precision": "exact", "text": "Cengizhan Mah., 1620/81 Sok., No:5, Bayraklı, İzmir, Türkiye", "kind": "house", "Address": {"country_code": "TR", "formatted": "Cengizhan Mah., 1620/81 Sok., No:5, Bayraklı, İzmir, Türkiye", "Components": [{"kind": "country", "name": "Türkiye"}, {"kind": "province", "name": "İzmir"}, {"kind": "area", "name": "Bayraklı"}, {"kind": "district", "name": "Cengizhan Mah."}, {"kind": "street", "name": "1620/81 Sok."}, {"kind": "house", "name": "No:5"}]}, "AddressDetails": {"Country": {"AddressLine": "Cengizhan Mah., 1620/81 Sok., No:5, Bayraklı, İzmir, Türkiye", "CountryNameCode": "TR", "CountryName": "Türkiye", "AdministrativeArea": {"AdministrativeAreaName": "İzmir", "SubAdministrativeArea": {"SubAdministrativeAreaName": "Bayraklı", "Locality": {"DependentLocality": {"DependentLocalityName": "Cengizhan Mah.", "Thoroughfare": {"ThoroughfareName": "1620/81 Sok.", "Premise": {"PremiseNumber": "No:5"}}}}}}}}}}, "name": "1620/81 Sok., No:5", "description": "Cengizhan Mah., Bayraklı, İzmir, Türkiye", "boundedBy": {"Envelope": {"lowerCorner": "27.155083 38.47197", "upperCorner": "27.163293 38.478424"}}, "uri": "ymapsbm1://geo?data=CgoyMzk2Mjk0MjY4EjxUw7xya2l5ZSwgxLB6bWlyLCBCYXlyYWtsxLEsIENlbmdpemhhbiBNYWguLCAxNjIwLzgxIFNvay4sIDUiCg0GRtlBFZvmGUI,", "Point": {"pos": "27.159188 38.475197"}}}]}}}