{"response": {"GeoObjectCollection": {"metaDataProperty": {"GeocoderResponseMetaData": {"request": "4274. Sk. No:62/2 AYDIN KARABAĞLAR İzmir", "results": "5", "found": "1"}}, "featureMember": [{"GeoObject": {"metaDataProperty": {"GeocoderMetaData": {"precision": "number", "text": "Aydın Mah., 4274 Sok., No:62, Karabağlar, İzmir, Türkiye", "kind": "house", "Address": {"country_code": "TR", "formatted": "Aydın Mah., 4274 Sok., No:62, Karabağlar, İzmir, Türkiye", "Components": [{"kind": "country", "name": "Türkiye"}, {"kind": "province", "name": "İzmir"}, {"kind": "area", "name": "Karabağlar"}, {"kind": "district", "name": "Aydın Mah."}, {"kind": "street", "name": "4274 Sok."}, {"kind": "house", "name": "No:62"}]}, "AddressDetails": {"Country": {"AddressLine": "Aydın Mah., 4274 Sok., No:62, Karabağlar, İzmir, Türkiye", "CountryNameCode": "TR", "CountryName": "Türkiye", "AdministrativeArea": {"AdministrativeAreaName": "İzmir", "SubAdministrativeArea": {"SubAdministrativeAreaName": "Karabağlar", "Locality": {"DependentLocality": {"DependentLocalityName": "Aydın Mah.", "Thoroughfare": {"ThoroughfareName": "4274 Sok.", "Premise": {"PremiseNumber": "No:62"}}}}}}}}}}, "name": "4274 Sok., No:62", "description": "Aydın Mah., Karabağlar, İzmir, Türkiye", "boundedBy": {"Envelope": {"lowerCorner": "27.129122 38.363633", "upperCorner": "27.137332 38.370098"}}, "uri": "ymapsbm1://geo?data=CgoyMzk3MjI0ODI1EjlUw7xya2l5ZSwgxLB6bWlyLCBLYXJhYmHEn2xhciwgQXlkxLFuIE1haC4sIDQyNzQgU29rLiwgNjIiCg3XENlBFax3GUI,", "Point": {"pos": "27.133227 38.366866"}}}]}}}